foliobutler/__init__.py
foliobutler/fb_api.py
foliobutler/ibc_default_ini
foliobutler/starter.py
foliobutler-0.51.dist-info/licenses/LICENSE
foliobutler-0.51.dist-info/METADATA
foliobutler-0.51.dist-info/WHEEL
foliobutler-0.51.dist-info/entry_points.txt
foliobutler-0.51.dist-info/top_level.txt
foliobutler-0.51.dist-info/RECORD
