Metadata-Version: 2.4
Name: foliobutler
Version: 0.51
Summary: Sync your Interactive Brokers account                   with your Folio in Foliobutler
Home-page: https://github.com/svenotremba/foliobutler
Author: Sven
Author-email: sven@foliobutler.com
License: MIT
License-File: LICENSE
Requires-Dist: setuptools
Requires-Dist: click
Requires-Dist: click_params
Requires-Dist: requests
Requires-Dist: ib_insync
Requires-Dist: python_dotenv
Dynamic: author
Dynamic: author-email
Dynamic: home-page
Dynamic: license
Dynamic: license-file
Dynamic: requires-dist
Dynamic: summary
